valorant_api/__init__.py
valorant_api/_version.py
valorant_api/agents.py
valorant_api/api.py
valorant_api/base_list.py
valorant_api/buddies.py
valorant_api/bundles.py
valorant_api/ceremonies.py
valorant_api/competitive.py
valorant_api/competitivetiers.py
valorant_api/contenttiers.py
valorant_api/contracts.py
valorant_api/currencies.py
valorant_api/endpoints.py
valorant_api/events.py
valorant_api/exceptions.py
valorant_api/gamemodes.py
valorant_api/gear.py
valorant_api/httpclient.py
valorant_api/levelborders.py
valorant_api/maps.py
valorant_api/playercards.py
valorant_api/playertitles.py
valorant_api/seasons.py
valorant_api/sprays.py
valorant_api/themes.py
valorant_api/utils.py
valorant_api/version.py
valorant_api/weapons.py
valorant_api_pillowless-0.0.3.dist-info/LICENSE
valorant_api_pillowless-0.0.3.dist-info/METADATA
valorant_api_pillowless-0.0.3.dist-info/WHEEL
valorant_api_pillowless-0.0.3.dist-info/top_level.txt
valorant_api_pillowless-0.0.3.dist-info/RECORD
