Metadata-Version: 2.1
Name: valorant-api-pillowless
Version: 0.0.3
Summary: Sync/Async Python wrapper for valorant-api.com without the pillow dependency
Author: Whitelisted
Project-URL: Homepage, https://github.com/Whitelisted1/valorant-api-pillowless
Project-URL: Issues, https://github.com/Whitelisted1/valorant-api-pillowless/issues
Classifier: Programming Language :: Python :: 3
Classifier: License :: OSI Approved :: MIT License
Classifier: Operating System :: OS Independent
Requires-Python: >=3.8
License-File: LICENSE
Requires-Dist: python-dateutil ==2.8.1
Requires-Dist: aiohttp >=3.10.1
Requires-Dist: requests >=2.32.3
